thanks/__init__.py
thanks/cli.py
thanks/thanks.json
thanks/thanks.py
thanks-0.0.8.dist-info/DESCRIPTION.rst
thanks-0.0.8.dist-info/METADATA
thanks-0.0.8.dist-info/RECORD
thanks-0.0.8.dist-info/WHEEL
thanks-0.0.8.dist-info/entry_points.txt
thanks-0.0.8.dist-info/metadata.json
thanks-0.0.8.dist-info/top_level.txt
