Metadata-Version: 2.0
Name: thanks
Version: 0.0.8
Summary: Finding ways to fund the packages you use.
Home-page: https://github.com/phildini/thanks
Author: Philip James
Author-email: phildini@phildini.net
License: Apache Software License 2.0
Project-URL: Funding, https://patreon.com/phildini
Project-URL: Source, https://github.com/phildini/thanks
Project-URL: Tracker, https://github.com/phildini/thanks/issues
Keywords: thanks
Platform: UNKNOWN
Classifier: Development Status :: 2 - Pre-Alpha
Classifier: Intended Audience :: Developers
Classifier: License :: OSI Approved :: Apache Software License
Classifier: Natural Language :: English
Classifier: Programming Language :: Python :: 2
Classifier: Programming Language :: Python :: 2.7
Classifier: Programming Language :: Python :: 3
Classifier: Programming Language :: Python :: 3.4
Classifier: Programming Language :: Python :: 3.5
Classifier: Programming Language :: Python :: 3.6
Requires-Dist: Click (>=6.0)
Requires-Dist: humanfriendly (==4.8)
Requires-Dist: requirements-parser (==0.2.0)
Requires-Dist: termcolor (==1.1.0)
